[
  {
    "id": "apeswap",
    "value": []
  },
  {
    "id": "cafeswap",
    "value": [
      {
        "stakeToken": "BREW",
        "APR": 91.35,
        "earnToken": "BREW",
        "depositFee": 0,
        "totalLiquidity": 2816119.76
      },
      {
        "stakeToken": "BREW",
        "APR": 220.31,
        "earnToken": "SQUID",
        "depositFee": 0,
        "totalLiquidity": 65518.384
      },
      {
        "stakeToken": "BREW",
        "APR": 116.8,
        "earnToken": "AXS",
        "depositFee": 0,
        "totalLiquidity": 7555.22
      },
      {
        "stakeToken": "BREW",
        "APR": 167.26,
        "earnToken": "AXS",
        "depositFee": 0,
        "totalLiquidity": 188767.337
      },
      {
        "stakeToken": "BREW",
        "APR": 233.16,
        "earnToken": "DUEL",
        "depositFee": 0,
        "totalLiquidity": 9636.117
      },
      {
        "stakeToken": "BREW",
        "APR": 171.56,
        "earnToken": "DUEL",
        "depositFee": 0,
        "totalLiquidity": 312858.518
      },
      {
        "stakeToken": "BREW",
        "APR": 18.61,
        "earnToken": "CZF",
        "depositFee": 0,
        "totalLiquidity": 1093.15
      },
      {
        "stakeToken": "BREW",
        "APR": 81.84,
        "earnToken": "CZF",
        "depositFee": 0,
        "totalLiquidity": 11874.543
      }
    ]
  },
  {
    "id": "goosedefi",
    "value": []
  },
  {
    "id": "kebabfinance",
    "value": []
  },
  {
    "id": "pancakeswap",
    "value": []
  },
  {
    "id": "pandayield",
    "value": [
      {
        "stakeToken": "BBOO",
        "APR": 69.35,
        "earnToken": "BBOO",
        "totalLiquidity": 29051.475
      }
    ]
  },
  {
    "id": "saltswap",
    "value": [
      {
        "stakeToken": "SALT",
        "APR": 35.26,
        "earnToken": "$0 (0%)",
        "depositFee": 18643,
        "totalLiquidity": 18643
      },
      {
        "stakeToken": "BUSD",
        "APR": 39.74,
        "earnToken": "$0 (0%)",
        "depositFee": 3308,
        "totalLiquidity": 3308
      },
      {
        "stakeToken": "WBNB",
        "APR": 12.64,
        "earnToken": "$0 (0%)",
        "depositFee": 5201,
        "totalLiquidity": 5201
      }
    ]
  },
  {
    "id": "slimefinance",
    "value": [
      {
        "stakeToken": "SLIME V2",
        "APR": 20.97,
        "earnToken": "Slime",
        "depositFee": 0,
        "totalLiquidity": 1993
      },
      {
        "stakeToken": "WBNB",
        "APR": 18.42,
        "earnToken": "Slime",
        "depositFee": 4,
        "totalLiquidity": 378
      },
      {
        "stakeToken": "BUSD",
        "APR": 15.61,
        "earnToken": "Slime",
        "depositFee": 4,
        "totalLiquidity": 223
      },
      {
        "stakeToken": "BTCB",
        "APR": 10.23,
        "earnToken": "Slime",
        "depositFee": 4,
        "totalLiquidity": 681
      },
      {
        "stakeToken": "ETH",
        "APR": 198.83,
        "earnToken": "Slime",
        "depositFee": 4,
        "totalLiquidity": 35
      },
      {
        "stakeToken": "DOT",
        "APR": 225.05,
        "earnToken": "Slime",
        "depositFee": 4,
        "totalLiquidity": 31
      },
      {
        "stakeToken": "ADA",
        "APR": 6.33,
        "earnToken": "Slime",
        "depositFee": 4,
        "totalLiquidity": 1101
      },
      {
        "stakeToken": "CAKE",
        "APR": 87.02,
        "earnToken": "Slime",
        "depositFee": 4,
        "totalLiquidity": 80
      },
      {
        "stakeToken": "LINK",
        "APR": 14.95,
        "earnToken": "Slime",
        "depositFee": 4,
        "totalLiquidity": 466
      },
      {
        "stakeToken": "ATOM",
        "APR": 10.73,
        "earnToken": "Slime",
        "depositFee": 4,
        "totalLiquidity": 649
      },
      {
        "stakeToken": "ZIL",
        "APR": 22.83,
        "earnToken": "Slime",
        "depositFee": 4,
        "totalLiquidity": 305
      },
      {
        "stakeToken": "LTC",
        "APR": 301.04,
        "earnToken": "Slime",
        "depositFee": 4,
        "totalLiquidity": 17
      },
      {
        "stakeToken": "MTSLA",
        "APR": 4.81,
        "earnToken": "Slime",
        "depositFee": 4,
        "totalLiquidity": 1085
      },
      {
        "stakeToken": "UNI",
        "APR": 15.68,
        "earnToken": "Slime",
        "depositFee": 4,
        "totalLiquidity": 333
      },
      {
        "stakeToken": "MIR",
        "APR": 3.37,
        "earnToken": "Slime",
        "depositFee": 4,
        "totalLiquidity": 1550
      },
      {
        "stakeToken": "UST",
        "APR": 3.28,
        "earnToken": "Slime",
        "depositFee": 4,
        "totalLiquidity": 1060
      },
      {
        "stakeToken": "USDT",
        "APR": 8.19,
        "earnToken": "Slime",
        "depositFee": 4,
        "totalLiquidity": 425
      },
      {
        "stakeToken": "DAI",
        "APR": 33.21,
        "earnToken": "Slime",
        "depositFee": 4,
        "totalLiquidity": 105
      },
      {
        "stakeToken": "DOGE",
        "APR": 4.05,
        "earnToken": "Slime",
        "depositFee": 4,
        "totalLiquidity": 1288
      }
    ]
  }
]