[
  {
    "id": "apeswap",
    "value": [
      {
        "stakeToken": "BANANA",
        "APR": 265.26,
        "earnToken": "BANANA",
        "totalLiquidity": 9670866.24
      },
      {
        "stakeToken": "JDI",
        "APR": 247.52,
        "earnToken": "JDI",
        "totalLiquidity": 82230.977
      },
      {
        "stakeToken": "LYPTUS",
        "APR": 260.21,
        "earnToken": "LYPTUS",
        "totalLiquidity": 48905.671
      },
      {
        "stakeToken": "FOXY",
        "APR": 384.19,
        "earnToken": "FOXY",
        "totalLiquidity": 84146.957
      },
      {
        "stakeToken": "NAUT",
        "APR": 624.72,
        "earnToken": "NAUT",
        "totalLiquidity": 0.184
      },
      {
        "stakeToken": "JDI",
        "APR": 120.75,
        "earnToken": "JDI",
        "totalLiquidity": 5762.135
      }
    ]
  },
  {
    "id": "blueswap",
    "value": [
      {
        "stakeToken": "BLUE",
        "APR": 93.72,
        "earnToken": "BLUE",
        "depositFee": 0,
        "totalLiquidity": 371666
      },
      {
        "stakeToken": "BUSD",
        "APR": 110.95,
        "earnToken": "BLUE",
        "depositFee": 2,
        "totalLiquidity": 125571
      },
      {
        "stakeToken": "WBNB",
        "APR": 160.12,
        "earnToken": "BLUE",
        "depositFee": 2,
        "totalLiquidity": 87012
      },
      {
        "stakeToken": "ETH",
        "APR": 84.84,
        "earnToken": "BLUE",
        "depositFee": 2,
        "totalLiquidity": 164228
      }
    ]
  },
  {
    "id": "cafeswap",
    "value": [
      {
        "stakeToken": "BREW",
        "APR": 308.82,
        "earnToken": "BREW",
        "depositFee": 0,
        "totalLiquidity": 828103.22
      },
      {
        "stakeToken": "BREW",
        "APR": 328.26,
        "earnToken": "NAUT",
        "depositFee": 0.5,
        "totalLiquidity": 27925.824
      },
      {
        "stakeToken": "BREW",
        "APR": 475.03,
        "earnToken": "3CS",
        "depositFee": 0.5,
        "totalLiquidity": 10541.513
      },
      {
        "stakeToken": "BREW",
        "APR": 468.98,
        "earnToken": "ITAM",
        "depositFee": 0.5,
        "totalLiquidity": 29592.46
      },
      {
        "stakeToken": "BREW",
        "APR": 324.33,
        "earnToken": "TWT",
        "depositFee": 0.5,
        "totalLiquidity": 15217.589
      }
    ]
  },
  {
    "id": "goosedefi",
    "value": [
      {
        "stakeToken": "EGG",
        "APR": 152.24,
        "earnToken": "EGG",
        "depositFee": 0,
        "totalLiquidity": 15709213
      },
      {
        "stakeToken": "BUSD",
        "APR": 67.14,
        "earnToken": "EGG",
        "depositFee": 1.5,
        "totalLiquidity": 2849386
      },
      {
        "stakeToken": "WBNB",
        "APR": 45.24,
        "earnToken": "EGG",
        "depositFee": 1.5,
        "totalLiquidity": 6343917
      },
      {
        "stakeToken": "USDT",
        "APR": 70.67,
        "earnToken": "EGG",
        "depositFee": 1.5,
        "totalLiquidity": 1353674
      },
      {
        "stakeToken": "BTCB",
        "APR": 32.65,
        "earnToken": "EGG",
        "depositFee": 1.5,
        "totalLiquidity": 5859802
      },
      {
        "stakeToken": "ETH",
        "APR": 37.62,
        "earnToken": "EGG",
        "depositFee": 1.5,
        "totalLiquidity": 5085422
      },
      {
        "stakeToken": "DAI",
        "APR": 77.05,
        "earnToken": "EGG",
        "depositFee": 1.5,
        "totalLiquidity": 1241473
      },
      {
        "stakeToken": "USDC",
        "APR": 70.77,
        "earnToken": "EGG",
        "depositFee": 1.5,
        "totalLiquidity": 1351738
      },
      {
        "stakeToken": "DOT",
        "APR": 54.68,
        "earnToken": "EGG",
        "depositFee": 1.5,
        "totalLiquidity": 3498659
      },
      {
        "stakeToken": "CAKE",
        "APR": 155.76,
        "earnToken": "EGG",
        "depositFee": 1.5,
        "totalLiquidity": 614158
      },
      {
        "stakeToken": "BSCX",
        "APR": 111.23,
        "earnToken": "EGG",
        "depositFee": 1.5,
        "totalLiquidity": 860008
      },
      {
        "stakeToken": "AUTO",
        "APR": 44.29,
        "earnToken": "EGG",
        "depositFee": 1.5,
        "totalLiquidity": 2159978
      }
    ]
  },
  {
    "id": "icebergdefi",
    "value": [
      {
        "stakeToken": "TIT",
        "APR": 394.76,
        "earnToken": "TIT",
        "depositFee": 0,
        "totalLiquidity": 525
      },
      {
        "stakeToken": "BUSD",
        "APR": 87.82,
        "earnToken": "TIT",
        "depositFee": 4,
        "totalLiquidity": 472
      },
      {
        "stakeToken": "WBNB",
        "APR": 51.74,
        "earnToken": "TIT",
        "depositFee": 4,
        "totalLiquidity": 1201
      },
      {
        "stakeToken": "USDT",
        "APR": 10.77,
        "earnToken": "TIT",
        "depositFee": 4,
        "totalLiquidity": 1923
      },
      {
        "stakeToken": "BTCB",
        "APR": 268,
        "earnToken": "TIT",
        "depositFee": 4,
        "totalLiquidity": 155
      },
      {
        "stakeToken": "ETH",
        "APR": 33.23,
        "earnToken": "TIT",
        "depositFee": 4,
        "totalLiquidity": 1246
      },
      {
        "stakeToken": "DAI",
        "APR": 785.81,
        "earnToken": "TIT",
        "depositFee": 4,
        "totalLiquidity": 26
      },
      {
        "stakeToken": "USDC",
        "APR": 622.98,
        "earnToken": "TIT",
        "depositFee": 4,
        "totalLiquidity": 33
      },
      {
        "stakeToken": "DOT",
        "APR": 44.81,
        "earnToken": "TIT",
        "depositFee": 4,
        "totalLiquidity": 924
      },
      {
        "stakeToken": "CAKE",
        "APR": 48.77,
        "earnToken": "TIT",
        "depositFee": 4,
        "totalLiquidity": 425
      },
      {
        "stakeToken": "UNI",
        "APR": 36.52,
        "earnToken": "TIT",
        "depositFee": 4,
        "totalLiquidity": 567
      },
      {
        "stakeToken": "AUTO",
        "APR": 799.29,
        "earnToken": "TIT",
        "depositFee": 4,
        "totalLiquidity": 26
      },
      {
        "stakeToken": "BDO",
        "APR": 34.41,
        "earnToken": "TIT",
        "depositFee": 4,
        "totalLiquidity": 602
      },
      {
        "stakeToken": "LINK",
        "APR": 36.19,
        "earnToken": "TIT",
        "depositFee": 4,
        "totalLiquidity": 572
      },
      {
        "stakeToken": "XVS",
        "APR": 2118.45,
        "earnToken": "TIT",
        "depositFee": 4,
        "totalLiquidity": 10
      },
      {
        "stakeToken": "BSCX",
        "APR": 1195.55,
        "earnToken": "TIT",
        "depositFee": 4,
        "totalLiquidity": 17
      }
    ]
  },
  {
    "id": "jigglyfinance",
    "value": [
      {
        "stakeToken": "JIGG",
        "APR": 125.07,
        "earnToken": "JIGG",
        "depositFee": 0,
        "totalLiquidity": 59195
      },
      {
        "stakeToken": "BUSD",
        "APR": 297.85,
        "earnToken": "JIGG",
        "depositFee": 4,
        "totalLiquidity": 4971
      },
      {
        "stakeToken": "WBNB",
        "APR": 42.44,
        "earnToken": "JIGG",
        "depositFee": 4,
        "totalLiquidity": 52339
      },
      {
        "stakeToken": "USDT",
        "APR": 110.55,
        "earnToken": "JIGG",
        "depositFee": 4,
        "totalLiquidity": 6697
      },
      {
        "stakeToken": "DAI",
        "APR": 184.96,
        "earnToken": "JIGG",
        "depositFee": 4,
        "totalLiquidity": 4003
      },
      {
        "stakeToken": "USDC",
        "APR": 164.94,
        "earnToken": "JIGG",
        "depositFee": 4,
        "totalLiquidity": 4489
      },
      {
        "stakeToken": "VAI",
        "APR": 116.29,
        "earnToken": "JIGG",
        "depositFee": 4,
        "totalLiquidity": 6367
      },
      {
        "stakeToken": "UST",
        "APR": 124.25,
        "earnToken": "JIGG",
        "depositFee": 4,
        "totalLiquidity": 5959
      },
      {
        "stakeToken": "BTCB",
        "APR": 118.93,
        "earnToken": "JIGG",
        "depositFee": 4,
        "totalLiquidity": 12451
      },
      {
        "stakeToken": "ETH",
        "APR": 49.11,
        "earnToken": "JIGG",
        "depositFee": 4,
        "totalLiquidity": 30151
      },
      {
        "stakeToken": "DOT",
        "APR": 52.32,
        "earnToken": "JIGG",
        "depositFee": 4,
        "totalLiquidity": 28302
      },
      {
        "stakeToken": "XVS",
        "APR": 86.73,
        "earnToken": "JIGG",
        "depositFee": 4,
        "totalLiquidity": 17074
      },
      {
        "stakeToken": "ADA",
        "APR": 50.5,
        "earnToken": "JIGG",
        "depositFee": 4,
        "totalLiquidity": 29323
      },
      {
        "stakeToken": "LINK",
        "APR": 20.2,
        "earnToken": "JIGG",
        "depositFee": 4,
        "totalLiquidity": 73292
      },
      {
        "stakeToken": "UNI",
        "APR": 69.94,
        "earnToken": "JIGG",
        "depositFee": 4,
        "totalLiquidity": 21171
      },
      {
        "stakeToken": "XRP",
        "APR": 79.64,
        "earnToken": "JIGG",
        "depositFee": 4,
        "totalLiquidity": 18592
      },
      {
        "stakeToken": "CAKE",
        "APR": 263.86,
        "earnToken": "JIGG",
        "depositFee": 4,
        "totalLiquidity": 5612
      },
      {
        "stakeToken": "EOS",
        "APR": 601.35,
        "earnToken": "JIGG",
        "depositFee": 4,
        "totalLiquidity": 2462
      },
      {
        "stakeToken": "AUTO",
        "APR": 301.1,
        "earnToken": "JIGG",
        "depositFee": 4,
        "totalLiquidity": 4918
      }
    ]
  },
  {
    "id": "kebabfinance",
    "value": [
      {
        "stakeToken": "KEBAB",
        "APR": 159.69,
        "earnToken": "KEBAB",
        "totalLiquidity": 1590972.959
      },
      {
        "stakeToken": "KEBAB",
        "APR": 140.77,
        "earnToken": "BTCB",
        "totalLiquidity": 60537.161
      },
      {
        "stakeToken": "KEBAB",
        "APR": 127.64,
        "earnToken": "BNB",
        "totalLiquidity": 52607.631
      }
    ]
  },
  {
    "id": "pancakeswap",
    "value": [
      {
        "stakeToken": "CAKE",
        "APR": 98.92,
        "earnToken": "CAKE",
        "totalLiquidity": 105200076.89
      },
      {
        "stakeToken": "CAKE",
        "APR": 89,
        "earnToken": "ARPA",
        "totalLiquidity": 59621.994
      },
      {
        "stakeToken": "CAKE",
        "APR": 78.45,
        "earnToken": "ITAM",
        "totalLiquidity": 169078.271
      },
      {
        "stakeToken": "CAKE",
        "APR": 65.56,
        "earnToken": "BONDLY",
        "totalLiquidity": 168466.932
      },
      {
        "stakeToken": "CAKE",
        "APR": 104.8,
        "earnToken": "TKO",
        "totalLiquidity": 1086650.08
      },
      {
        "stakeToken": "CAKE",
        "APR": 97.31,
        "earnToken": "APYS",
        "totalLiquidity": 118071.795
      },
      {
        "stakeToken": "CAKE",
        "APR": 105.65,
        "earnToken": "HOO",
        "totalLiquidity": 120617.314
      },
      {
        "stakeToken": "CAKE",
        "APR": 100.02,
        "earnToken": "ODDZ",
        "totalLiquidity": 131745.317
      },
      {
        "stakeToken": "CAKE",
        "APR": 100.87,
        "earnToken": "EASY",
        "totalLiquidity": 97558.066
      },
      {
        "stakeToken": "CAKE",
        "APR": 110.38,
        "earnToken": "NRV",
        "totalLiquidity": 274752.054
      },
      {
        "stakeToken": "CAKE",
        "APR": 75.6,
        "earnToken": "DEGO",
        "totalLiquidity": 43861.337
      },
      {
        "stakeToken": "CAKE",
        "APR": 102.61,
        "earnToken": "GUM",
        "totalLiquidity": 89682.559
      },
      {
        "stakeToken": "CAKE",
        "APR": 85.2,
        "earnToken": "pBTC",
        "totalLiquidity": 96132.393
      },
      {
        "stakeToken": "CAKE",
        "APR": 107.34,
        "earnToken": "DFT",
        "totalLiquidity": 190286.151
      },
      {
        "stakeToken": "CAKE",
        "APR": 107.87,
        "earnToken": "SWTH",
        "totalLiquidity": 72327.345
      },
      {
        "stakeToken": "CAKE",
        "APR": 104.77,
        "earnToken": "LIEN",
        "totalLiquidity": 80460.145
      },
      {
        "stakeToken": "CAKE",
        "APR": 84.65,
        "earnToken": "ZIL",
        "totalLiquidity": 117965.059
      },
      {
        "stakeToken": "CAKE",
        "APR": 94.5,
        "earnToken": "pCWS",
        "totalLiquidity": 69763.483
      },
      {
        "stakeToken": "CAKE",
        "APR": 89.16,
        "earnToken": "bBadger",
        "totalLiquidity": 68530.495
      },
      {
        "stakeToken": "CAKE",
        "APR": 104.34,
        "earnToken": "bDIGG",
        "totalLiquidity": 42920.339
      },
      {
        "stakeToken": "CAKE",
        "APR": 110.16,
        "earnToken": "LTO",
        "totalLiquidity": 87032.409
      },
      {
        "stakeToken": "CAKE",
        "APR": 78.83,
        "earnToken": "MIR",
        "totalLiquidity": 85517.026
      },
      {
        "stakeToken": "CAKE",
        "APR": 105.06,
        "earnToken": "TRADE",
        "totalLiquidity": 142692.021
      },
      {
        "stakeToken": "CAKE",
        "APR": 104.45,
        "earnToken": "DUSK",
        "totalLiquidity": 72158.123
      },
      {
        "stakeToken": "CAKE",
        "APR": 91.4,
        "earnToken": "BIFI",
        "totalLiquidity": 67004.634
      },
      {
        "stakeToken": "CAKE",
        "APR": 111.64,
        "earnToken": "TXL",
        "totalLiquidity": 102143.403
      },
      {
        "stakeToken": "CAKE",
        "APR": 100.17,
        "earnToken": "COS",
        "totalLiquidity": 98749.676
      },
      {
        "stakeToken": "CAKE",
        "APR": 95.32,
        "earnToken": "BUNNY",
        "totalLiquidity": 469710.121
      },
      {
        "stakeToken": "CAKE",
        "APR": 105.69,
        "earnToken": "ALICE",
        "totalLiquidity": 757855.663
      },
      {
        "stakeToken": "CAKE",
        "APR": 100.27,
        "earnToken": "FOR",
        "totalLiquidity": 160146.356
      },
      {
        "stakeToken": "CAKE",
        "APR": 105.66,
        "earnToken": "BUX",
        "totalLiquidity": 175012.493
      },
      {
        "stakeToken": "CAKE",
        "APR": 92.63,
        "earnToken": "NULS",
        "totalLiquidity": 56861.567
      },
      {
        "stakeToken": "CAKE",
        "APR": 107.36,
        "earnToken": "BELT",
        "totalLiquidity": 424060.434
      },
      {
        "stakeToken": "CAKE",
        "APR": 102.44,
        "earnToken": "RAMP",
        "totalLiquidity": 170119.184
      },
      {
        "stakeToken": "CAKE",
        "APR": 109.58,
        "earnToken": "BFI",
        "totalLiquidity": 28779.121
      },
      {
        "stakeToken": "CAKE",
        "APR": 102.6,
        "earnToken": "DEXE",
        "totalLiquidity": 101709.388
      },
      {
        "stakeToken": "CAKE",
        "APR": 102.49,
        "earnToken": "BEL",
        "totalLiquidity": 118711.646
      },
      {
        "stakeToken": "CAKE",
        "APR": 102.44,
        "earnToken": "TPT",
        "totalLiquidity": 52963.661
      },
      {
        "stakeToken": "CAKE",
        "APR": 103.31,
        "earnToken": "WATCH",
        "totalLiquidity": 205367.717
      },
      {
        "stakeToken": "CAKE",
        "APR": 103.79,
        "earnToken": "xMARK",
        "totalLiquidity": 102684.254
      },
      {
        "stakeToken": "CAKE",
        "APR": 109.23,
        "earnToken": "bMXX",
        "totalLiquidity": 26226.937
      },
      {
        "stakeToken": "CAKE",
        "APR": 104.3,
        "earnToken": "IOTX",
        "totalLiquidity": 132013.741
      },
      {
        "stakeToken": "CAKE",
        "APR": 106.32,
        "earnToken": "BOR",
        "totalLiquidity": 143541.353
      },
      {
        "stakeToken": "CAKE",
        "APR": 96.62,
        "earnToken": "bOPEN",
        "totalLiquidity": 89509.533
      },
      {
        "stakeToken": "CAKE",
        "APR": 102.21,
        "earnToken": "DODO",
        "totalLiquidity": 100894.771
      },
      {
        "stakeToken": "CAKE",
        "APR": 104.98,
        "earnToken": "SWINGBY",
        "totalLiquidity": 31871.954
      },
      {
        "stakeToken": "CAKE",
        "APR": 103.28,
        "earnToken": "BRY",
        "totalLiquidity": 351347.1
      },
      {
        "stakeToken": "CAKE",
        "APR": 107.06,
        "earnToken": "SWGb",
        "totalLiquidity": 222506.425
      },
      {
        "stakeToken": "CAKE",
        "APR": 70.36,
        "earnToken": "DITTO",
        "totalLiquidity": 7254.04
      }
    ]
  },
  {
    "id": "pandayield",
    "value": [
      {
        "stakeToken": "BBOO",
        "APR": 161.24,
        "earnToken": "BBOO",
        "totalLiquidity": 2206270.752
      }
    ]
  },
  {
    "id": "saltswap",
    "value": [
      {
        "stakeToken": "SALT",
        "APR": 261.75,
        "earnToken": "SALT",
        "depositFee": 0,
        "totalLiquidity": 125016
      },
      {
        "stakeToken": "BUSD",
        "APR": 75.58,
        "earnToken": "SALT",
        "depositFee": 1.5,
        "totalLiquidity": 86589
      },
      {
        "stakeToken": "WBNB",
        "APR": 38.4,
        "earnToken": "SALT",
        "depositFee": 1.5,
        "totalLiquidity": 85212
      }
    ]
  },
  {
    "id": "slimefinance",
    "value": []
  }
]