[
  {
    "stakeToken": "BUNNY",
    "earnToken": "BUNNY",
    "totalLiquidity": 34322916.88,
    "APY": 80.31
  },
  {
    "stakeToken": "BUNNY-BNB LP",
    "earnToken": "CAKE + BUNNY",
    "totalLiquidity": 6326902.36,
    "APY": 118.14
  },
  {
    "stakeToken": "bQBT",
    "earnToken": "QBT + BUNNY",
    "totalLiquidity": 923679.35,
    "APY": 140.57
  },
  {
    "stakeToken": "bQBT-BNB LP",
    "earnToken": "QBT + BUNNY",
    "totalLiquidity": 643618.16,
    "APY": 250.04
  },
  {
    "stakeToken": "CAKE",
    "earnToken": "CAKE + BUNNY",
    "totalLiquidity": 130195016.65,
    "APY": 83.5
  },
  {
    "stakeToken": "CAKE",
    "earnToken": "QBT + BUNNY",
    "totalLiquidity": 1236094.98,
    "APY": 73.46
  },
  {
    "stakeToken": "QBT-BNB LP",
    "earnToken": "CAKE + BUNNY",
    "totalLiquidity": 2950025.47,
    "APY": 141.75
  },
  {
    "stakeToken": "CAKE-BNB LP",
    "earnToken": "CAKE-BNB LP + BUNNY",
    "totalLiquidity": 3464603.89,
    "APY": 45.87
  },
  {
    "stakeToken": "CAKE-BNB LP",
    "earnToken": "CAKE + BUNNY",
    "totalLiquidity": 219865193.2,
    "APY": 51.8
  },
  {
    "stakeToken": "BTCB-BNB LP",
    "earnToken": "BTCB-BNB LP + BUNNY",
    "totalLiquidity": 333872.42,
    "APY": 15.1
  },
  {
    "stakeToken": "BTCB-BNB LP",
    "earnToken": "CAKE + BUNNY",
    "totalLiquidity": 5981740.36,
    "APY": 18.17
  },
  {
    "stakeToken": "ETH-BNB LP",
    "earnToken": "ETH-BNB LP + BUNNY",
    "totalLiquidity": 313217.89,
    "APY": 16.14
  },
  {
    "stakeToken": "ETH-BNB LP",
    "earnToken": "CAKE + BUNNY",
    "totalLiquidity": 7479179.35,
    "APY": 18.95
  },
  {
    "stakeToken": "BUSD-BNB LP",
    "earnToken": "BUSD-BNB LP + BUNNY",
    "totalLiquidity": 673769.33,
    "APY": 31.56
  },
  {
    "stakeToken": "BUSD-BNB LP",
    "earnToken": "CAKE + BUNNY",
    "totalLiquidity": 9380102.27,
    "APY": 35.83
  },
  {
    "stakeToken": "USDT-BNB LP",
    "earnToken": "USDT-BNB LP + BUNNY",
    "totalLiquidity": 576205.34,
    "APY": 31.04
  },
  {
    "stakeToken": "USDT-BNB LP",
    "earnToken": "CAKE + BUNNY",
    "totalLiquidity": 4354189.79,
    "APY": 35.1
  },
  {
    "stakeToken": "USDT-BUSD LP",
    "earnToken": "USDT-BUSD LP + BUNNY",
    "totalLiquidity": 220071.2,
    "APY": 9.73
  },
  {
    "stakeToken": "USDT-BUSD LP",
    "earnToken": "CAKE + BUNNY",
    "totalLiquidity": 7136831.24,
    "APY": 11.65
  },
  {
    "stakeToken": "DOT-BNB LP",
    "earnToken": "CAKE + BUNNY",
    "totalLiquidity": 752028.53,
    "APY": 17.24
  },
  {
    "stakeToken": "BTCB-BUSD LP",
    "earnToken": "CAKE + BUNNY",
    "totalLiquidity": 3331634.09,
    "APY": 22.44
  },
  {
    "stakeToken": "DAI-BUSD LP",
    "earnToken": "CAKE + BUNNY",
    "totalLiquidity": 37102.5,
    "APY": 8.61
  },
  {
    "stakeToken": "USDC-BUSD LP",
    "earnToken": "CAKE + BUNNY",
    "totalLiquidity": 588880.66,
    "APY": 8.29
  },
  {
    "stakeToken": "VAI-BUSD LP",
    "earnToken": "VAI-BUSD LP + BUNNY",
    "totalLiquidity": 45695.85,
    "APY": 55.94
  },
  {
    "stakeToken": "VAI-BUSD LP",
    "earnToken": "CAKE + BUNNY",
    "totalLiquidity": 304463.58,
    "APY": 57.95
  },
  {
    "stakeToken": "BNB",
    "earnToken": "QBT + BUNNY",
    "totalLiquidity": 44555880.39,
    "APY": 12.83
  },
  {
    "stakeToken": "BUSD",
    "earnToken": "QBT + BUNNY",
    "totalLiquidity": 24459719.7,
    "APY": 21.26
  },
  {
    "stakeToken": "USDT",
    "earnToken": "QBT + BUNNY",
    "totalLiquidity": 25191775.28,
    "APY": 16.87
  },
  {
    "stakeToken": "DAI",
    "earnToken": "QBT + BUNNY",
    "totalLiquidity": 4349266.82,
    "APY": 15.12
  },
  {
    "stakeToken": "USDC",
    "earnToken": "QBT + BUNNY",
    "totalLiquidity": 15703277.97,
    "APY": 21.62
  },
  {
    "stakeToken": "BTCB",
    "earnToken": "QBT + BUNNY",
    "totalLiquidity": 58596069.06,
    "APY": 8.89
  },
  {
    "stakeToken": "ETH",
    "earnToken": "QBT + BUNNY",
    "totalLiquidity": 29380347.46,
    "APY": 13.11
  }
]