[
  {
    "stakeToken": "BUNNY",
    "earnToken": "BUNNY",
    "totalLiquidity": 85189309.74,
    "APY": 265.23
  },
  {
    "stakeToken": "BUNNY-BNB FLIP",
    "earnToken": "CAKE + BUNNY",
    "totalLiquidity": 98675564.55,
    "APY": 255.51
  },
  {
    "stakeToken": "BUNNY",
    "earnToken": "WBNB",
    "totalLiquidity": 230123480.83,
    "APY": 325.09
  },
  {
    "stakeToken": "CAKE",
    "earnToken": "CAKE + BUNNY",
    "totalLiquidity": 1799911416.41,
    "APY": 164.92
  },
  {
    "stakeToken": "CAKE-BNB FLIP",
    "earnToken": "CAKE-BNB FLIP + BUNNY",
    "totalLiquidity": 48411177.01,
    "APY": 98.09
  },
  {
    "stakeToken": "CAKE-BNB FLIP",
    "earnToken": "CAKE + BUNNY",
    "totalLiquidity": 691509562.02,
    "APY": 115.2
  },
  {
    "stakeToken": "BTCB-BNB FLIP",
    "earnToken": "BTCB-BNB FLIP + BUNNY",
    "totalLiquidity": 2304829.22,
    "APY": 21.6
  },
  {
    "stakeToken": "BTCB-BNB FLIP",
    "earnToken": "CAKE + BUNNY",
    "totalLiquidity": 160062524.61,
    "APY": 28.64
  },
  {
    "stakeToken": "ETH-BNB FLIP",
    "earnToken": "ETH-BNB FLIP + BUNNY",
    "totalLiquidity": 3086613.49,
    "APY": 26.28
  },
  {
    "stakeToken": "ETH-BNB FLIP",
    "earnToken": "CAKE + BUNNY",
    "totalLiquidity": 123661834.69,
    "APY": 32.47
  },
  {
    "stakeToken": "BUSD-BNB FLIP",
    "earnToken": "BUSD-BNB FLIP + BUNNY",
    "totalLiquidity": 3019828.66,
    "APY": 57.49
  },
  {
    "stakeToken": "BUSD-BNB FLIP",
    "earnToken": "CAKE + BUNNY",
    "totalLiquidity": 534220112.19,
    "APY": 67.88
  },
  {
    "stakeToken": "USDT-BNB FLIP",
    "earnToken": "USDT-BNB FLIP + BUNNY",
    "totalLiquidity": 817571.24,
    "APY": 57.9
  },
  {
    "stakeToken": "USDT-BNB FLIP",
    "earnToken": "CAKE + BUNNY",
    "totalLiquidity": 154993994.11,
    "APY": 68.55
  },
  {
    "stakeToken": "USDT-BUSD FLIP",
    "earnToken": "USDT-BUSD FLIP + BUNNY",
    "totalLiquidity": 1312235.46,
    "APY": 17.52
  },
  {
    "stakeToken": "USDT-BUSD FLIP",
    "earnToken": "CAKE + BUNNY",
    "totalLiquidity": 185531335.85,
    "APY": 23.84
  },
  {
    "stakeToken": "VAI-BUSD FLIP",
    "earnToken": "VAI-BUSD FLIP + BUNNY",
    "totalLiquidity": 306860.38,
    "APY": 20.21
  },
  {
    "stakeToken": "VAI-BUSD FLIP",
    "earnToken": "CAKE + BUNNY",
    "totalLiquidity": 51016969.04,
    "APY": 27.44
  },
  {
    "stakeToken": "BNB",
    "earnToken": "BNB + BUNNY",
    "totalLiquidity": 323413098.89,
    "APY": 16.5
  },
  {
    "stakeToken": "ETH",
    "earnToken": "ETH + BUNNY",
    "totalLiquidity": 185954607.81,
    "APY": 4.8
  },
  {
    "stakeToken": "BTCB",
    "earnToken": "BTCB + BUNNY",
    "totalLiquidity": 268855515.95,
    "APY": 15.29
  },
  {
    "stakeToken": "USDT",
    "earnToken": "USDT + BUNNY",
    "totalLiquidity": 471382755.74,
    "APY": 33.88
  },
  {
    "stakeToken": "BUSD",
    "earnToken": "BUSD + BUNNY",
    "totalLiquidity": 339318936.29,
    "APY": 28.55
  }
]