[
  {
    "stakeToken": "pBUNNY",
    "earnToken": "BNB + BUNNY + CAKE",
    "totalLiquidity": 0,
    "APY": 18318449
  },
  {
    "stakeToken": "BUNNY",
    "earnToken": "BUNNY",
    "totalLiquidity": 91667295.57,
    "APY": 221.6
  },
  {
    "stakeToken": "BUNNY-BNB FLIP",
    "earnToken": "CAKE + BUNNY",
    "totalLiquidity": 14503456.35,
    "APY": 216.04
  },
  {
    "stakeToken": "BUNNY",
    "earnToken": "WBNB",
    "totalLiquidity": 129548101.55,
    "APY": 221.6
  },
  {
    "stakeToken": "QBT-BNB FLIP",
    "earnToken": "QBT",
    "totalLiquidity": 19030914.82,
    "APY": 1630.17
  },
  {
    "stakeToken": "CAKE",
    "earnToken": "CAKE + BUNNY",
    "totalLiquidity": 187721455.15,
    "APY": 106.78
  },
  {
    "stakeToken": "CAKE-BNB FLIP",
    "earnToken": "CAKE-BNB FLIP + BUNNY",
    "totalLiquidity": 9728126.16,
    "APY": 74.26
  },
  {
    "stakeToken": "CAKE-BNB FLIP",
    "earnToken": "CAKE + BUNNY",
    "totalLiquidity": 218260285.58,
    "APY": 81.79
  },
  {
    "stakeToken": "BTCB-BNB FLIP",
    "earnToken": "BTCB-BNB FLIP + BUNNY",
    "totalLiquidity": 403765.39,
    "APY": 15.72
  },
  {
    "stakeToken": "BTCB-BNB FLIP",
    "earnToken": "CAKE + BUNNY",
    "totalLiquidity": 4562443.3,
    "APY": 20.34
  },
  {
    "stakeToken": "ETH-BNB FLIP",
    "earnToken": "ETH-BNB FLIP + BUNNY",
    "totalLiquidity": 843375.69,
    "APY": 17.27
  },
  {
    "stakeToken": "ETH-BNB FLIP",
    "earnToken": "CAKE + BUNNY",
    "totalLiquidity": 9003191.35,
    "APY": 21.49
  },
  {
    "stakeToken": "DOT-BNB FLIP",
    "earnToken": "CAKE + BUNNY",
    "totalLiquidity": 250923.42,
    "APY": 35.13
  },
  {
    "stakeToken": "BUSD-BNB FLIP",
    "earnToken": "BUSD-BNB FLIP + BUNNY",
    "totalLiquidity": 315577.17,
    "APY": 27.01
  },
  {
    "stakeToken": "BUSD-BNB FLIP",
    "earnToken": "CAKE + BUNNY",
    "totalLiquidity": 18387886.11,
    "APY": 32.47
  },
  {
    "stakeToken": "USDT-BNB FLIP",
    "earnToken": "USDT-BNB FLIP + BUNNY",
    "totalLiquidity": 689802.24,
    "APY": 26.5
  },
  {
    "stakeToken": "USDT-BNB FLIP",
    "earnToken": "CAKE + BUNNY",
    "totalLiquidity": 9596283.05,
    "APY": 31.64
  },
  {
    "stakeToken": "BTCB-BUSD FLIP",
    "earnToken": "CAKE + BUNNY",
    "totalLiquidity": 85740.16,
    "APY": 19.92
  },
  {
    "stakeToken": "USDT-BUSD FLIP",
    "earnToken": "USDT-BUSD FLIP + BUNNY",
    "totalLiquidity": 516479.16,
    "APY": 9.81
  },
  {
    "stakeToken": "USDT-BUSD FLIP",
    "earnToken": "CAKE + BUNNY",
    "totalLiquidity": 32350135.49,
    "APY": 12.79
  },
  {
    "stakeToken": "VAI-BUSD FLIP",
    "earnToken": "VAI-BUSD FLIP + BUNNY",
    "totalLiquidity": 114250.36,
    "APY": 12.86
  },
  {
    "stakeToken": "VAI-BUSD FLIP",
    "earnToken": "CAKE + BUNNY",
    "totalLiquidity": 4694649.09,
    "APY": 17.26
  },
  {
    "stakeToken": "DAI-BUSD FLIP",
    "earnToken": "CAKE + BUNNY",
    "totalLiquidity": 1829972.91,
    "APY": 12.89
  },
  {
    "stakeToken": "USDC-BUSD FLIP",
    "earnToken": "CAKE + BUNNY",
    "totalLiquidity": 4499885.62,
    "APY": 11.3
  },
  {
    "stakeToken": "BNB",
    "earnToken": "BNB + BUNNY",
    "totalLiquidity": 34207573.96,
    "APY": 8.96
  },
  {
    "stakeToken": "ETH",
    "earnToken": "ETH + BUNNY",
    "totalLiquidity": 4339006.12,
    "APY": 1.31
  },
  {
    "stakeToken": "BTCB",
    "earnToken": "BTCB + BUNNY",
    "totalLiquidity": 8602904.85,
    "APY": 2
  },
  {
    "stakeToken": "USDT",
    "earnToken": "USDT + BUNNY",
    "totalLiquidity": 8560465.86,
    "APY": 9.64
  },
  {
    "stakeToken": "BUSD",
    "earnToken": "BUSD + BUNNY",
    "totalLiquidity": 5783788.19,
    "APY": 6.94
  }
]