[
  {
    "stakeToken": "BUNNY",
    "earnToken": "BUNNY",
    "totalLiquidity": 66227644.61,
    "APY": 103.26
  },
  {
    "stakeToken": "BUNNY-BNB FLIP",
    "earnToken": "CAKE + BUNNY",
    "totalLiquidity": 10984465.86,
    "APY": 216.12
  },
  {
    "stakeToken": "QBT-BNB FLIP",
    "earnToken": "QBT",
    "totalLiquidity": 29360412.95,
    "APY": 1320.07
  },
  {
    "stakeToken": "CAKE",
    "earnToken": "CAKE + BUNNY",
    "totalLiquidity": 213062658.98,
    "APY": 98.78
  },
  {
    "stakeToken": "CAKE-BNB FLIP",
    "earnToken": "CAKE-BNB FLIP + BUNNY",
    "totalLiquidity": 7322455.74,
    "APY": 70.41
  },
  {
    "stakeToken": "CAKE-BNB FLIP",
    "earnToken": "CAKE + BUNNY",
    "totalLiquidity": 287599787.02,
    "APY": 76.81
  },
  {
    "stakeToken": "BTCB-BNB FLIP",
    "earnToken": "BTCB-BNB FLIP + BUNNY",
    "totalLiquidity": 440678.02,
    "APY": 26.57
  },
  {
    "stakeToken": "BTCB-BNB FLIP",
    "earnToken": "CAKE + BUNNY",
    "totalLiquidity": 5825624.98,
    "APY": 32.83
  },
  {
    "stakeToken": "ETH-BNB FLIP",
    "earnToken": "ETH-BNB FLIP + BUNNY",
    "totalLiquidity": 550321,
    "APY": 19.65
  },
  {
    "stakeToken": "ETH-BNB FLIP",
    "earnToken": "CAKE + BUNNY",
    "totalLiquidity": 8644289.65,
    "APY": 24.29
  },
  {
    "stakeToken": "DOT-BNB FLIP",
    "earnToken": "CAKE + BUNNY",
    "totalLiquidity": 465237.87,
    "APY": 25.11
  },
  {
    "stakeToken": "BUSD-BNB FLIP",
    "earnToken": "BUSD-BNB FLIP + BUNNY",
    "totalLiquidity": 313088.13,
    "APY": 51.75
  },
  {
    "stakeToken": "BUSD-BNB FLIP",
    "earnToken": "CAKE + BUNNY",
    "totalLiquidity": 14340991.4,
    "APY": 59.22
  },
  {
    "stakeToken": "USDT-BNB FLIP",
    "earnToken": "USDT-BNB FLIP + BUNNY",
    "totalLiquidity": 610984.74,
    "APY": 68.73
  },
  {
    "stakeToken": "USDT-BNB FLIP",
    "earnToken": "CAKE + BUNNY",
    "totalLiquidity": 7247916.37,
    "APY": 76.53
  },
  {
    "stakeToken": "BTCB-BUSD FLIP",
    "earnToken": "CAKE + BUNNY",
    "totalLiquidity": 43708.28,
    "APY": 41.84
  },
  {
    "stakeToken": "USDT-BUSD FLIP",
    "earnToken": "USDT-BUSD FLIP + BUNNY",
    "totalLiquidity": 1466320.78,
    "APY": 12.35
  },
  {
    "stakeToken": "USDT-BUSD FLIP",
    "earnToken": "CAKE + BUNNY",
    "totalLiquidity": 12076287.72,
    "APY": 15.4
  },
  {
    "stakeToken": "VAI-BUSD FLIP",
    "earnToken": "VAI-BUSD FLIP + BUNNY",
    "totalLiquidity": 101231.87,
    "APY": 9.03
  },
  {
    "stakeToken": "VAI-BUSD FLIP",
    "earnToken": "CAKE + BUNNY",
    "totalLiquidity": 3284653.02,
    "APY": 11.2
  },
  {
    "stakeToken": "DAI-BUSD FLIP",
    "earnToken": "CAKE + BUNNY",
    "totalLiquidity": 1105729.1,
    "APY": 4.48
  },
  {
    "stakeToken": "USDC-BUSD FLIP",
    "earnToken": "CAKE + BUNNY",
    "totalLiquidity": 2451513.54,
    "APY": 12.74
  },
  {
    "stakeToken": "BNB",
    "earnToken": "BNB + BUNNY",
    "totalLiquidity": 13088810.83,
    "APY": 4.82
  },
  {
    "stakeToken": "ETH",
    "earnToken": "ETH + BUNNY",
    "totalLiquidity": 4472921.11,
    "APY": 1.38
  },
  {
    "stakeToken": "BTCB",
    "earnToken": "BTCB + BUNNY",
    "totalLiquidity": 8042984.24,
    "APY": 2.63
  },
  {
    "stakeToken": "USDT",
    "earnToken": "USDT + BUNNY",
    "totalLiquidity": 15975938.03,
    "APY": 11.88
  },
  {
    "stakeToken": "BUSD",
    "earnToken": "BUSD + BUNNY",
    "totalLiquidity": 4901381.91,
    "APY": 6.29
  }
]