[
  {
    "stakeToken": "BUNNY",
    "earnToken": "BUNNY",
    "totalLiquidity": 66788037.56,
    "APY": 91.44
  },
  {
    "stakeToken": "BUNNY-BNB FLIP",
    "earnToken": "CAKE + BUNNY",
    "totalLiquidity": 11009791.01,
    "APY": 154.24
  },
  {
    "stakeToken": "QBT-BNB FLIP",
    "earnToken": "QBT",
    "totalLiquidity": 31793662.92,
    "APY": 1032.66
  },
  {
    "stakeToken": "QBT-BNB FLIP",
    "earnToken": "CAKE + BUNNY",
    "totalLiquidity": 1536770.47,
    "APY": 258.96
  },
  {
    "stakeToken": "CAKE",
    "earnToken": "CAKE + BUNNY",
    "totalLiquidity": 198231676.85,
    "APY": 95.6
  },
  {
    "stakeToken": "CAKE-BNB FLIP",
    "earnToken": "CAKE-BNB FLIP + BUNNY",
    "totalLiquidity": 6352172.51,
    "APY": 46.18
  },
  {
    "stakeToken": "CAKE-BNB FLIP",
    "earnToken": "CAKE + BUNNY",
    "totalLiquidity": 292903318.18,
    "APY": 53.8
  },
  {
    "stakeToken": "BTCB-BNB FLIP",
    "earnToken": "BTCB-BNB FLIP + BUNNY",
    "totalLiquidity": 470828.37,
    "APY": 17.4
  },
  {
    "stakeToken": "BTCB-BNB FLIP",
    "earnToken": "CAKE + BUNNY",
    "totalLiquidity": 4697676.76,
    "APY": 21.7
  },
  {
    "stakeToken": "ETH-BNB FLIP",
    "earnToken": "ETH-BNB FLIP + BUNNY",
    "totalLiquidity": 565005.59,
    "APY": 14.38
  },
  {
    "stakeToken": "ETH-BNB FLIP",
    "earnToken": "CAKE + BUNNY",
    "totalLiquidity": 12352136.04,
    "APY": 17.33
  },
  {
    "stakeToken": "DOT-BNB FLIP",
    "earnToken": "CAKE + BUNNY",
    "totalLiquidity": 492954.45,
    "APY": 24.8
  },
  {
    "stakeToken": "BUSD-BNB FLIP",
    "earnToken": "BUSD-BNB FLIP + BUNNY",
    "totalLiquidity": 332852.82,
    "APY": 36.48
  },
  {
    "stakeToken": "BUSD-BNB FLIP",
    "earnToken": "CAKE + BUNNY",
    "totalLiquidity": 13853072.03,
    "APY": 42.25
  },
  {
    "stakeToken": "USDT-BNB FLIP",
    "earnToken": "USDT-BNB FLIP + BUNNY",
    "totalLiquidity": 622865.65,
    "APY": 36.18
  },
  {
    "stakeToken": "USDT-BNB FLIP",
    "earnToken": "CAKE + BUNNY",
    "totalLiquidity": 6110404.97,
    "APY": 41.83
  },
  {
    "stakeToken": "BTCB-BUSD FLIP",
    "earnToken": "CAKE + BUNNY",
    "totalLiquidity": 3027879.79,
    "APY": 31.04
  },
  {
    "stakeToken": "USDT-BUSD FLIP",
    "earnToken": "USDT-BUSD FLIP + BUNNY",
    "totalLiquidity": 1474316.5,
    "APY": 10.79
  },
  {
    "stakeToken": "USDT-BUSD FLIP",
    "earnToken": "CAKE + BUNNY",
    "totalLiquidity": 11774032.41,
    "APY": 13.48
  },
  {
    "stakeToken": "VAI-BUSD FLIP",
    "earnToken": "VAI-BUSD FLIP + BUNNY",
    "totalLiquidity": 59119.71,
    "APY": 7.68
  },
  {
    "stakeToken": "VAI-BUSD FLIP",
    "earnToken": "CAKE + BUNNY",
    "totalLiquidity": 2857715.47,
    "APY": 9.1
  },
  {
    "stakeToken": "DAI-BUSD FLIP",
    "earnToken": "CAKE + BUNNY",
    "totalLiquidity": 1038578.06,
    "APY": 12
  },
  {
    "stakeToken": "USDC-BUSD FLIP",
    "earnToken": "CAKE + BUNNY",
    "totalLiquidity": 1190225.88,
    "APY": 11.35
  },
  {
    "stakeToken": "BNB",
    "earnToken": "BNB + BUNNY",
    "totalLiquidity": 10982971.79,
    "APY": 4.91
  },
  {
    "stakeToken": "ETH",
    "earnToken": "ETH + BUNNY",
    "totalLiquidity": 5177827.74,
    "APY": 1.31
  },
  {
    "stakeToken": "BTCB",
    "earnToken": "BTCB + BUNNY",
    "totalLiquidity": 8112149.72,
    "APY": 2.68
  },
  {
    "stakeToken": "USDT",
    "earnToken": "USDT + BUNNY",
    "totalLiquidity": 14107268.92,
    "APY": 7.44
  },
  {
    "stakeToken": "BUSD",
    "earnToken": "BUSD + BUNNY",
    "totalLiquidity": 4846174.7,
    "APY": 8.64
  }
]